ragrank/__init__.py
ragrank/_api.py
ragrank/_version.py
ragrank/agents/__init__.py
ragrank/agents/base.py
ragrank/agents/eval_agent.py
ragrank/bridge/__init__.py
ragrank/bridge/langchain.py
ragrank/bridge/pydante.py
ragrank/cache.py
ragrank/callbacks.py
ragrank/config/__init__.py
ragrank/config/base.py
ragrank/config/run_config.py
ragrank/constants.py
ragrank/dataset/__init__.py
ragrank/dataset/base.py
ragrank/dataset/generator.py
ragrank/decorators.py
ragrank/embedding/__init__.py
ragrank/embedding/base.py
ragrank/embedding/langchain.py
ragrank/evaluation.py
ragrank/exceptions.py
ragrank/integration/__init__.py
ragrank/llm/__init__.py
ragrank/llm/base.py
ragrank/llm/langchain.py
ragrank/llm/openai.py
ragrank/logger.py
ragrank/metrics/__init__.py
ragrank/metrics/base.py
ragrank/metrics/context_relevancy.py
ragrank/prompt/__init__.py
ragrank/prompt/base.py
ragrank/prompt/templates.py
ragrank/runner.py
ragrank/utils/__init__.py
ragrank/utils/common.py
ragrank/utils/template.py
ragrank/validation/__init__.py
ragrank/validation/base.py
ragrank/validation/datase_validator.py
ragrank/validation/embedding_validator.py
ragrank/validation/llm_validator.py
ragrank/validation/metric_validator.py
ragrank-0.1.1.dist-info/LICENSE
ragrank-0.1.1.dist-info/METADATA
ragrank-0.1.1.dist-info/WHEEL
ragrank-0.1.1.dist-info/RECORD
