Metadata-Version: 2.1
Name: ragrank
Version: 0.1.1
Summary: An evaluation libarary for RAG models
Home-page: https://github.com/Auto-Playground/RAGrank
License: Apache-2.0
Keywords: rag,evaluation
Author: Izam Mohammed
Author-email: izamdeveloper1@gmail.com
Requires-Python: >=3.9,<4.0
Classifier: License :: OSI Approved :: Apache Software License
Classifier: Programming Language :: Python :: 3
Classifier: Programming Language :: Python :: 3.9
Classifier: Programming Language :: Python :: 3.10
Classifier: Programming Language :: Python :: 3.11
Requires-Dist: numpy (>=1.26.4,<2.0.0)
Requires-Dist: pathlib (>=1.0.1,<2.0.0)
Requires-Dist: requests (>=2.28.2,<3.0.0,!=2.30.0)
Requires-Dist: requests-toolbelt (>=1.0.0,<2.0.0)
Requires-Dist: urllib3 (>=2.2.1,<3.0.0)
Project-URL: Repository, https://github.com/Auto-Playground/RAGrank
